[
 {
   "시장명": "남해전통시장",
   "시장유형": "상설장",
   "소재지도로명주소": "경상남도 남해군 남해읍 화전로 110",
   "소재지지번주소": "경상남도 남해군 남해읍 북변리 282-11",
   "시장개설주기": "2,  7일",
   "위도": 34.8429229119,
   "경도": 127.895263454,
   "점포수": 105,
   "취급품목": "농산물, 생필품, 수산물, 잡화 등",
   "사용가능상품권": "온누리상품권",
   "홈페이지주소": "http://남해전통시장.com",
   "공중화장실보유여부": "Y",
   "주차장보유여부": "Y",
   "개설년도": 1978,
   "전화번호": "055-864-3592",
   "데이터기준일자": "2019-06-21"
 },
 {
   "시장명": "이동공설시장",
   "시장유형": "5일장",
   "소재지도로명주소": "경상남도 남해군 이동면 무림로 63번길9",
   "소재지지번주소": "경상남도 남해군 이동면 무림리 1140",
   "시장개설주기": "5, 10일",
   "위도": 34.8008531895,
   "경도": 127.953771,
   "점포수": 28,
   "취급품목": "농산물, 수산물",
   "사용가능상품권": "온누리상품권",
   "홈페이지주소": "",
   "공중화장실보유여부": "Y",
   "주차장보유여부": "Y",
   "개설년도": 1933,
   "전화번호": "",
   "데이터기준일자": "2019-06-21"
 },
 {
   "시장명": "지족공설시장",
   "시장유형": "5일장",
   "소재지도로명주소": "경상남도 남해군 삼동면 동부대로 1876번길 30-1",
   "소재지지번주소": "경상남도 남해군 삼동면 지족리 200-7",
   "시장개설주기": "1,  6일",
   "위도": 34.8307016,
   "경도": 128.0030164,
   "점포수": 11,
   "취급품목": "어패류, 멸치",
   "사용가능상품권": "온누리상품권",
   "홈페이지주소": "",
   "공중화장실보유여부": "Y",
   "주차장보유여부": "Y",
   "개설년도": 1957,
   "전화번호": "",
   "데이터기준일자": "2019-06-21"
 },
 {
   "시장명": "남면공설시장",
   "시장유형": "5일장",
   "소재지도로명주소": "경상남도 남해군 남면 남서대로 785-4",
   "소재지지번주소": "경상남도 남해군 남면 당항리 1381-5",
   "시장개설주기": "4,  9일",
   "위도": 34.7709242774,
   "경도": 127.8854754652,
   "점포수": 18,
   "취급품목": "어패류, 농산물",
   "사용가능상품권": "온누리상품권",
   "홈페이지주소": "",
   "공중화장실보유여부": "Y",
   "주차장보유여부": "Y",
   "개설년도": 1961,
   "전화번호": "",
   "데이터기준일자": "2019-06-21"
 },
 {
   "시장명": "고현공성시장",
   "시장유형": "5일장",
   "소재지도로명주소": "경상남도 남해군 고현면 탑동로 68-2",
   "소재지지번주소": "경상남도 남해군 고현면 대사리 768",
   "시장개설주기": "3,  8일",
   "위도": 34.8971428054,
   "경도": 127.872859,
   "점포수": 26,
   "취급품목": "농산물",
   "사용가능상품권": "온누리상품권",
   "홈페이지주소": "",
   "공중화장실보유여부": "Y",
   "주차장보유여부": "Y",
   "개설년도": 1946,
   "전화번호": "",
   "데이터기준일자": "2019-06-21"
 }
]